odoo/addons/website_sale_require_legal/README.rst
odoo/addons/website_sale_require_legal/__init__.py
odoo/addons/website_sale_require_legal/__manifest__.py
odoo/addons/website_sale_require_legal/controllers/__init__.py
odoo/addons/website_sale_require_legal/controllers/main.py
odoo/addons/website_sale_require_legal/demo/assets.xml
odoo/addons/website_sale_require_legal/i18n/de.po
odoo/addons/website_sale_require_legal/i18n/es.po
odoo/addons/website_sale_require_legal/i18n/hr.po
odoo/addons/website_sale_require_legal/i18n/it.po
odoo/addons/website_sale_require_legal/i18n/sl.po
odoo/addons/website_sale_require_legal/i18n/website_sale_require_legal.pot
odoo/addons/website_sale_require_legal/readme/CONFIGURE.rst
odoo/addons/website_sale_require_legal/readme/CONTRIBUTORS.rst
odoo/addons/website_sale_require_legal/readme/DESCRIPTION.rst
odoo/addons/website_sale_require_legal/readme/INSTALL.rst
odoo/addons/website_sale_require_legal/readme/ROADMAP.rst
odoo/addons/website_sale_require_legal/readme/USAGE.rst
odoo/addons/website_sale_require_legal/static/description/icon.png
odoo/addons/website_sale_require_legal/static/description/index.html
odoo/addons/website_sale_require_legal/static/src/js/tour.js
odoo/addons/website_sale_require_legal/tests/__init__.py
odoo/addons/website_sale_require_legal/tests/test_ui.py
odoo/addons/website_sale_require_legal/views/website_sale.xml
odoo11_addon_website_sale_require_legal-11.0.1.0.0.99.dev5.dist-info/METADATA
odoo11_addon_website_sale_require_legal-11.0.1.0.0.99.dev5.dist-info/WHEEL
odoo11_addon_website_sale_require_legal-11.0.1.0.0.99.dev5.dist-info/top_level.txt
odoo11_addon_website_sale_require_legal-11.0.1.0.0.99.dev5.dist-info/RECORD
